momo_BMI_Test/BMI_Test.py
momo_BMI_Test-0.0.0.5.dist-info/METADATA
momo_BMI_Test-0.0.0.5.dist-info/WHEEL
momo_BMI_Test-0.0.0.5.dist-info/top_level.txt
momo_BMI_Test-0.0.0.5.dist-info/RECORD
